bitlist/__init__.py
bitlist/bitlist.py
py3bitlist-1.0.2.dist-info/DESCRIPTION.rst
py3bitlist-1.0.2.dist-info/METADATA
py3bitlist-1.0.2.dist-info/RECORD
py3bitlist-1.0.2.dist-info/WHEEL
py3bitlist-1.0.2.dist-info/metadata.json
py3bitlist-1.0.2.dist-info/top_level.txt
