Metadata-Version: 2.0
Name: py3bitlist
Version: 1.0.2
Summary: An bits array implement in pure python.
Home-page: https://github.com/coneco/BitList/
Author: coNEco
Author-email: coneco@outlook.com
License: MIT
Provides-Extra: dev
Provides-Extra: test
